microondas/codificador_input/HDL/terceiro_nivel/clk_freq.v
module clk_freq(input clk_in, output reg clk_out = 0);
  reg [6:0] contador = 0;

  always @(posedge clk_in) begin
    if (contador == 99) begin
      contador <= 0; 
      clk_out <= ~clk_out; 
    end else begin
      contador <= contador + 1;
    end
  end

endmodule

microondas/codificador_input/teste/clk_freq/clk_freq_tb.v
`timescale 1ns/1ps
`include "codificador_input\HDL\terceiro_nivel\clk_freq.v"

module clk_freq_tb;
    reg clk_in; wire clk_out;
    integer  i;

    clk_freq dut (
        .clk_in(clk_in), .clk_out(clk_out)
    );

    initial begin
        $dumpfile("clk_freq.vcd");
        $dumpvars(0, clk_freq_tb);

        /* como o objetivo é diminuir a frequência do relógio de 100Hz para 1 Hz, o esperado é que
        o relógio pulse 3 vezes e não 300 */

        clk_in = 0;
        for (i = 0; i < 600; i = i + 1) begin
          #10 clk_in = ~clk_in;
        end

      	$finish;
    end
endmodule

microondas/codificador_input/teste/clk_freq/clk_freq.vcd
$date
	Sun Apr 23 14:44:11 2023
$end
$version
	Icarus Verilog
$end
$timescale
	1ps
$end
$scope module clk_freq_tb $end
$var wire 1 ! clk_out $end
$var reg 1 " clk_in $end
$var integer 32 # i [31:0] $end
$scope module dut $end
$var wire 1 " clk_in $end
$var reg 1 ! clk_out $end
$var reg 7 $ contador [6:0] $end
$upscope $end
$upscope $end
$enddefinitions $end
#0
$dumpvars
b0 $
b0 #
0"
0!
$end
#10000
b1 $
b1 #
1"
#20000
b10 #
0"
#30000
b10 $
b11 #
1"
#40000
b100 #
0"
#50000
b11 $
b101 #
1"
#60000
b110 #
0"
#70000
b100 $
b111 #
1"
#80000
b1000 #
0"
#90000
b101 $
b1001 #
1"
#100000
b1010 #
0"
#110000
b110 $
b1011 #
1"
#120000
b1100 #
0"
#130000
b111 $
b1101 #
1"
#140000
b1110 #
0"
#150000
b1000 $
b1111 #
1"
#160000
b10000 #
0"
#170000
b1001 $
b10001 #
1"
#180000
b10010 #
0"
#190000
b1010 $
b10011 #
1"
#200000
b10100 #
0"
#210000
b1011 $
b10101 #
1"
#220000
b10110 #
0"
#230000
b1100 $
b10111 #
1"
#240000
b11000 #
0"
#250000
b1101 $
b11001 #
1"
#260000
b11010 #
0"
#270000
b1110 $
b11011 #
1"
#280000
b11100 #
0"
#290000
b1111 $
b11101 #
1"
#300000
b11110 #
0"
#310000
b10000 $
b11111 #
1"
#320000
b100000 #
0"
#330000
b10001 $
b100001 #
1"
#340000
b100010 #
0"
#350000
b10010 $
b100011 #
1"
#360000
b100100 #
0"
#370000
b10011 $
b100101 #
1"
#380000
b100110 #
0"
#390000
b10100 $
b100111 #
1"
#400000
b101000 #
0"
#410000
b10101 $
b101001 #
1"
#420000
b101010 #
0"
#430000
b10110 $
b101011 #
1"
#440000
b101100 #
0"
#450000
b10111 $
b101101 #
1"
#460000
b101110 #
0"
#470000
b11000 $
b101111 #
1"
#480000
b110000 #
0"
#490000
b11001 $
b110001 #
1"
#500000
b110010 #
0"
#510000
b11010 $
b110011 #
1"
#520000
b110100 #
0"
#530000
b11011 $
b110101 #
1"
#540000
b110110 #
0"
#550000
b11100 $
b110111 #
1"
#560000
b111000 #
0"
#570000
b11101 $
b111001 #
1"
#580000
b111010 #
0"
#590000
b11110 $
b111011 #
1"
#600000
b111100 #
0"
#610000
b11111 $
b111101 #
1"
#620000
b111110 #
0"
#630000
b100000 $
b111111 #
1"
#640000
b1000000 #
0"
#650000
b100001 $
b1000001 #
1"
#660000
b1000010 #
0"
#670000
b100010 $
b1000011 #
1"
#680000
b1000100 #
0"
#690000
b100011 $
b1000101 #
1"
#700000
b1000110 #
0"
#710000
b100100 $
b1000111 #
1"
#720000
b1001000 #
0"
#730000
b100101 $
b1001001 #
1"
#740000
b1001010 #
0"
#750000
b100110 $
b1001011 #
1"
#760000
b1001100 #
0"
#770000
b100111 $
b1001101 #
1"
#780000
b1001110 #
0"
#790000
b101000 $
b1001111 #
1"
#800000
b1010000 #
0"
#810000
b101001 $
b1010001 #
1"
#820000
b1010010 #
0"
#830000
b101010 $
b1010011 #
1"
#840000
b1010100 #
0"
#850000
b101011 $
b1010101 #
1"
#860000
b1010110 #
0"
#870000
b101100 $
b1010111 #
1"
#880000
b1011000 #
0"
#890000
b101101 $
b1011001 #
1"
#900000
b1011010 #
0"
#910000
b101110 $
b1011011 #
1"
#920000
b1011100 #
0"
#930000
b101111 $
b1011101 #
1"
#940000
b1011110 #
0"
#950000
b110000 $
b1011111 #
1"
#960000
b1100000 #
0"
#970000
b110001 $
b1100001 #
1"
#980000
b1100010 #
0"
#990000
b110010 $
b1100011 #
1"
#1000000
b1100100 #
0"
#1010000
b110011 $
b1100101 #
1"
#1020000
b1100110 #
0"
#1030000
b110100 $
b1100111 #
1"
#1040000
b1101000 #
0"
#1050000
b110101 $
b1101001 #
1"
#1060000
b1101010 #
0"
#1070000
b110110 $
b1101011 #
1"
#1080000
b1101100 #
0"
#1090000
b110111 $
b1101101 #
1"
#1100000
b1101110 #
0"
#1110000
b111000 $
b1101111 #
1"
#1120000
b1110000 #
0"
#1130000
b111001 $
b1110001 #
1"
#1140000
b1110010 #
0"
#1150000
b111010 $
b1110011 #
1"
#1160000
b1110100 #
0"
#1170000
b111011 $
b1110101 #
1"
#1180000
b1110110 #
0"
#1190000
b111100 $
b1110111 #
1"
#1200000
b1111000 #
0"
#1210000
b111101 $
b1111001 #
1"
#1220000
b1111010 #
0"
#1230000
b111110 $
b1111011 #
1"
#1240000
b1111100 #
0"
#1250000
b111111 $
b1111101 #
1"
#1260000
b1111110 #
0"
#1270000
b1000000 $
b1111111 #
1"
#1280000
b10000000 #
0"
#1290000
b1000001 $
b10000001 #
1"
#1300000
b10000010 #
0"
#1310000
b1000010 $
b10000011 #
1"
#1320000
b10000100 #
0"
#1330000
b1000011 $
b10000101 #
1"
#1340000
b10000110 #
0"
#1350000
b1000100 $
b10000111 #
1"
#1360000
b10001000 #
0"
#1370000
b1000101 $
b10001001 #
1"
#1380000
b10001010 #
0"
#1390000
b1000110 $
b10001011 #
1"
#1400000
b10001100 #
0"
#1410000
b1000111 $
b10001101 #
1"
#1420000
b10001110 #
0"
#1430000
b1001000 $
b10001111 #
1"
#1440000
b10010000 #
0"
#1450000
b1001001 $
b10010001 #
1"
#1460000
b10010010 #
0"
#1470000
b1001010 $
b10010011 #
1"
#1480000
b10010100 #
0"
#1490000
b1001011 $
b10010101 #
1"
#1500000
b10010110 #
0"
#1510000
b1001100 $
b10010111 #
1"
#1520000
b10011000 #
0"
#1530000
b1001101 $
b10011001 #
1"
#1540000
b10011010 #
0"
#1550000
b1001110 $
b10011011 #
1"
#1560000
b10011100 #
0"
#1570000
b1001111 $
b10011101 #
1"
#1580000
b10011110 #
0"
#1590000
b1010000 $
b10011111 #
1"
#1600000
b10100000 #
0"
#1610000
b1010001 $
b10100001 #
1"
#1620000
b10100010 #
0"
#1630000
b1010010 $
b10100011 #
1"
#1640000
b10100100 #
0"
#1650000
b1010011 $
b10100101 #
1"
#1660000
b10100110 #
0"
#1670000
b1010100 $
b10100111 #
1"
#1680000
b10101000 #
0"
#1690000
b1010101 $
b10101001 #
1"
#1700000
b10101010 #
0"
#1710000
b1010110 $
b10101011 #
1"
#1720000
b10101100 #
0"
#1730000
b1010111 $
b10101101 #
1"
#1740000
b10101110 #
0"
#1750000
b1011000 $
b10101111 #
1"
#1760000
b10110000 #
0"
#1770000
b1011001 $
b10110001 #
1"
#1780000
b10110010 #
0"
#1790000
b1011010 $
b10110011 #
1"
#1800000
b10110100 #
0"
#1810000
b1011011 $
b10110101 #
1"
#1820000
b10110110 #
0"
#1830000
b1011100 $
b10110111 #
1"
#1840000
b10111000 #
0"
#1850000
b1011101 $
b10111001 #
1"
#1860000
b10111010 #
0"
#1870000
b1011110 $
b10111011 #
1"
#1880000
b10111100 #
0"
#1890000
b1011111 $
b10111101 #
1"
#1900000
b10111110 #
0"
#1910000
b1100000 $
b10111111 #
1"
#1920000
b11000000 #
0"
#1930000
b1100001 $
b11000001 #
1"
#1940000
b11000010 #
0"
#1950000
b1100010 $
b11000011 #
1"
#1960000
b11000100 #
0"
#1970000
b1100011 $
b11000101 #
1"
#1980000
b11000110 #
0"
#1990000
1!
b0 $
b11000111 #
1"
#2000000
b11001000 #
0"
#2010000
b1 $
b11001001 #
1"
#2020000
b11001010 #
0"
#2030000
b10 $
b11001011 #
1"
#2040000
b11001100 #
0"
#2050000
b11 $
b11001101 #
1"
#2060000
b11001110 #
0"
#2070000
b100 $
b11001111 #
1"
#2080000
b11010000 #
0"
#2090000
b101 $
b11010001 #
1"
#2100000
b11010010 #
0"
#2110000
b110 $
b11010011 #
1"
#2120000
b11010100 #
0"
#2130000
b111 $
b11010101 #
1"
#2140000
b11010110 #
0"
#2150000
b1000 $
b11010111 #
1"
#2160000
b11011000 #
0"
#2170000
b1001 $
b11011001 #
1"
#2180000
b11011010 #
0"
#2190000
b1010 $
b11011011 #
1"
#2200000
b11011100 #
0"
#2210000
b1011 $
b11011101 #
1"
#2220000
b11011110 #
0"
#2230000
b1100 $
b11011111 #
1"
#2240000
b11100000 #
0"
#2250000
b1101 $
b11100001 #
1"
#2260000
b11100010 #
0"
#2270000
b1110 $
b11100011 #
1"
#2280000
b11100100 #
0"
#2290000
b1111 $
b11100101 #
1"
#2300000
b11100110 #
0"
#2310000
b10000 $
b11100111 #
1"
#2320000
b11101000 #
0"
#2330000
b10001 $
b11101001 #
1"
#2340000
b11101010 #
0"
#2350000
b10010 $
b11101011 #
1"
#2360000
b11101100 #
0"
#2370000
b10011 $
b11101101 #
1"
#2380000
b11101110 #
0"
#2390000
b10100 $
b11101111 #
1"
#2400000
b11110000 #
0"
#2410000
b10101 $
b11110001 #
1"
#2420000
b11110010 #
0"
#2430000
b10110 $
b11110011 #
1"
#2440000
b11110100 #
0"
#2450000
b10111 $
b11110101 #
1"
#2460000
b11110110 #
0"
#2470000
b11000 $
b11110111 #
1"
#2480000
b11111000 #
0"
#2490000
b11001 $
b11111001 #
1"
#2500000
b11111010 #
0"
#2510000
b11010 $
b11111011 #
1"
#2520000
b11111100 #
0"
#2530000
b11011 $
b11111101 #
1"
#2540000
b11111110 #
0"
#2550000
b11100 $
b11111111 #
1"
#2560000
b100000000 #
0"
#2570000
b11101 $
b100000001 #
1"
#2580000
b100000010 #
0"
#2590000
b11110 $
b100000011 #
1"
#2600000
b100000100 #
0"
#2610000
b11111 $
b100000101 #
1"
#2620000
b100000110 #
0"
#2630000
b100000 $
b100000111 #
1"
#2640000
b100001000 #
0"
#2650000
b100001 $
b100001001 #
1"
#2660000
b100001010 #
0"
#2670000
b100010 $
b100001011 #
1"
#2680000
b100001100 #
0"
#2690000
b100011 $
b100001101 #
1"
#2700000
b100001110 #
0"
#2710000
b100100 $
b100001111 #
1"
#2720000
b100010000 #
0"
#2730000
b100101 $
b100010001 #
1"
#2740000
b100010010 #
0"
#2750000
b100110 $
b100010011 #
1"
#2760000
b100010100 #
0"
#2770000
b100111 $
b100010101 #
1"
#2780000
b100010110 #
0"
#2790000
b101000 $
b100010111 #
1"
#2800000
b100011000 #
0"
#2810000
b101001 $
b100011001 #
1"
#2820000
b100011010 #
0"
#2830000
b101010 $
b100011011 #
1"
#2840000
b100011100 #
0"
#2850000
b101011 $
b100011101 #
1"
#2860000
b100011110 #
0"
#2870000
b101100 $
b100011111 #
1"
#2880000
b100100000 #
0"
#2890000
b101101 $
b100100001 #
1"
#2900000
b100100010 #
0"
#2910000
b101110 $
b100100011 #
1"
#2920000
b100100100 #
0"
#2930000
b101111 $
b100100101 #
1"
#2940000
b100100110 #
0"
#2950000
b110000 $
b100100111 #
1"
#2960000
b100101000 #
0"
#2970000
b110001 $
b100101001 #
1"
#2980000
b100101010 #
0"
#2990000
b110010 $
b100101011 #
1"
#3000000
b100101100 #
0"
#3010000
b110011 $
b100101101 #
1"
#3020000
b100101110 #
0"
#3030000
b110100 $
b100101111 #
1"
#3040000
b100110000 #
0"
#3050000
b110101 $
b100110001 #
1"
#3060000
b100110010 #
0"
#3070000
b110110 $
b100110011 #
1"
#3080000
b100110100 #
0"
#3090000
b110111 $
b100110101 #
1"
#3100000
b100110110 #
0"
#3110000
b111000 $
b100110111 #
1"
#3120000
b100111000 #
0"
#3130000
b111001 $
b100111001 #
1"
#3140000
b100111010 #
0"
#3150000
b111010 $
b100111011 #
1"
#3160000
b100111100 #
0"
#3170000
b111011 $
b100111101 #
1"
#3180000
b100111110 #
0"
#3190000
b111100 $
b100111111 #
1"
#3200000
b101000000 #
0"
#3210000
b111101 $
b101000001 #
1"
#3220000
b101000010 #
0"
#3230000
b111110 $
b101000011 #
1"
#3240000
b101000100 #
0"
#3250000
b111111 $
b101000101 #
1"
#3260000
b101000110 #
0"
#3270000
b1000000 $
b101000111 #
1"
#3280000
b101001000 #
0"
#3290000
b1000001 $
b101001001 #
1"
#3300000
b101001010 #
0"
#3310000
b1000010 $
b101001011 #
1"
#3320000
b101001100 #
0"
#3330000
b1000011 $
b101001101 #
1"
#3340000
b101001110 #
0"
#3350000
b1000100 $
b101001111 #
1"
#3360000
b101010000 #
0"
#3370000
b1000101 $
b101010001 #
1"
#3380000
b101010010 #
0"
#3390000
b1000110 $
b101010011 #
1"
#3400000
b101010100 #
0"
#3410000
b1000111 $
b101010101 #
1"
#3420000
b101010110 #
0"
#3430000
b1001000 $
b101010111 #
1"
#3440000
b101011000 #
0"
#3450000
b1001001 $
b101011001 #
1"
#3460000
b101011010 #
0"
#3470000
b1001010 $
b101011011 #
1"
#3480000
b101011100 #
0"
#3490000
b1001011 $
b101011101 #
1"
#3500000
b101011110 #
0"
#3510000
b1001100 $
b101011111 #
1"
#3520000
b101100000 #
0"
#3530000
b1001101 $
b101100001 #
1"
#3540000
b101100010 #
0"
#3550000
b1001110 $
b101100011 #
1"
#3560000
b101100100 #
0"
#3570000
b1001111 $
b101100101 #
1"
#3580000
b101100110 #
0"
#3590000
b1010000 $
b101100111 #
1"
#3600000
b101101000 #
0"
#3610000
b1010001 $
b101101001 #
1"
#3620000
b101101010 #
0"
#3630000
b1010010 $
b101101011 #
1"
#3640000
b101101100 #
0"
#3650000
b1010011 $
b101101101 #
1"
#3660000
b101101110 #
0"
#3670000
b1010100 $
b101101111 #
1"
#3680000
b101110000 #
0"
#3690000
b1010101 $
b101110001 #
1"
#3700000
b101110010 #
0"
#3710000
b1010110 $
b101110011 #
1"
#3720000
b101110100 #
0"
#3730000
b1010111 $
b101110101 #
1"
#3740000
b101110110 #
0"
#3750000
b1011000 $
b101110111 #
1"
#3760000
b101111000 #
0"
#3770000
b1011001 $
b101111001 #
1"
#3780000
b101111010 #
0"
#3790000
b1011010 $
b101111011 #
1"
#3800000
b101111100 #
0"
#3810000
b1011011 $
b101111101 #
1"
#3820000
b101111110 #
0"
#3830000
b1011100 $
b101111111 #
1"
#3840000
b110000000 #
0"
#3850000
b1011101 $
b110000001 #
1"
#3860000
b110000010 #
0"
#3870000
b1011110 $
b110000011 #
1"
#3880000
b110000100 #
0"
#3890000
b1011111 $
b110000101 #
1"
#3900000
b110000110 #
0"
#3910000
b1100000 $
b110000111 #
1"
#3920000
b110001000 #
0"
#3930000
b1100001 $
b110001001 #
1"
#3940000
b110001010 #
0"
#3950000
b1100010 $
b110001011 #
1"
#3960000
b110001100 #
0"
#3970000
b1100011 $
b110001101 #
1"
#3980000
b110001110 #
0"
#3990000
0!
b0 $
b110001111 #
1"
#4000000
b110010000 #
0"
#4010000
b1 $
b110010001 #
1"
#4020000
b110010010 #
0"
#4030000
b10 $
b110010011 #
1"
#4040000
b110010100 #
0"
#4050000
b11 $
b110010101 #
1"
#4060000
b110010110 #
0"
#4070000
b100 $
b110010111 #
1"
#4080000
b110011000 #
0"
#4090000
b101 $
b110011001 #
1"
#4100000
b110011010 #
0"
#4110000
b110 $
b110011011 #
1"
#4120000
b110011100 #
0"
#4130000
b111 $
b110011101 #
1"
#4140000
b110011110 #
0"
#4150000
b1000 $
b110011111 #
1"
#4160000
b110100000 #
0"
#4170000
b1001 $
b110100001 #
1"
#4180000
b110100010 #
0"
#4190000
b1010 $
b110100011 #
1"
#4200000
b110100100 #
0"
#4210000
b1011 $
b110100101 #
1"
#4220000
b110100110 #
0"
#4230000
b1100 $
b110100111 #
1"
#4240000
b110101000 #
0"
#4250000
b1101 $
b110101001 #
1"
#4260000
b110101010 #
0"
#4270000
b1110 $
b110101011 #
1"
#4280000
b110101100 #
0"
#4290000
b1111 $
b110101101 #
1"
#4300000
b110101110 #
0"
#4310000
b10000 $
b110101111 #
1"
#4320000
b110110000 #
0"
#4330000
b10001 $
b110110001 #
1"
#4340000
b110110010 #
0"
#4350000
b10010 $
b110110011 #
1"
#4360000
b110110100 #
0"
#4370000
b10011 $
b110110101 #
1"
#4380000
b110110110 #
0"
#4390000
b10100 $
b110110111 #
1"
#4400000
b110111000 #
0"
#4410000
b10101 $
b110111001 #
1"
#4420000
b110111010 #
0"
#4430000
b10110 $
b110111011 #
1"
#4440000
b110111100 #
0"
#4450000
b10111 $
b110111101 #
1"
#4460000
b110111110 #
0"
#4470000
b11000 $
b110111111 #
1"
#4480000
b111000000 #
0"
#4490000
b11001 $
b111000001 #
1"
#4500000
b111000010 #
0"
#4510000
b11010 $
b111000011 #
1"
#4520000
b111000100 #
0"
#4530000
b11011 $
b111000101 #
1"
#4540000
b111000110 #
0"
#4550000
b11100 $
b111000111 #
1"
#4560000
b111001000 #
0"
#4570000
b11101 $
b111001001 #
1"
#4580000
b111001010 #
0"
#4590000
b11110 $
b111001011 #
1"
#4600000
b111001100 #
0"
#4610000
b11111 $
b111001101 #
1"
#4620000
b111001110 #
0"
#4630000
b100000 $
b111001111 #
1"
#4640000
b111010000 #
0"
#4650000
b100001 $
b111010001 #
1"
#4660000
b111010010 #
0"
#4670000
b100010 $
b111010011 #
1"
#4680000
b111010100 #
0"
#4690000
b100011 $
b111010101 #
1"
#4700000
b111010110 #
0"
#4710000
b100100 $
b111010111 #
1"
#4720000
b111011000 #
0"
#4730000
b100101 $
b111011001 #
1"
#4740000
b111011010 #
0"
#4750000
b100110 $
b111011011 #
1"
#4760000
b111011100 #
0"
#4770000
b100111 $
b111011101 #
1"
#4780000
b111011110 #
0"
#4790000
b101000 $
b111011111 #
1"
#4800000
b111100000 #
0"
#4810000
b101001 $
b111100001 #
1"
#4820000
b111100010 #
0"
#4830000
b101010 $
b111100011 #
1"
#4840000
b111100100 #
0"
#4850000
b101011 $
b111100101 #
1"
#4860000
b111100110 #
0"
#4870000
b101100 $
b111100111 #
1"
#4880000
b111101000 #
0"
#4890000
b101101 $
b111101001 #
1"
#4900000
b111101010 #
0"
#4910000
b101110 $
b111101011 #
1"
#4920000
b111101100 #
0"
#4930000
b101111 $
b111101101 #
1"
#4940000
b111101110 #
0"
#4950000
b110000 $
b111101111 #
1"
#4960000
b111110000 #
0"
#4970000
b110001 $
b111110001 #
1"
#4980000
b111110010 #
0"
#4990000
b110010 $
b111110011 #
1"
#5000000
b111110100 #
0"
#5010000
b110011 $
b111110101 #
1"
#5020000
b111110110 #
0"
#5030000
b110100 $
b111110111 #
1"
#5040000
b111111000 #
0"
#5050000
b110101 $
b111111001 #
1"
#5060000
b111111010 #
0"
#5070000
b110110 $
b111111011 #
1"
#5080000
b111111100 #
0"
#5090000
b110111 $
b111111101 #
1"
#5100000
b111111110 #
0"
#5110000
b111000 $
b111111111 #
1"
#5120000
b1000000000 #
0"
#5130000
b111001 $
b1000000001 #
1"
#5140000
b1000000010 #
0"
#5150000
b111010 $
b1000000011 #
1"
#5160000
b1000000100 #
0"
#5170000
b111011 $
b1000000101 #
1"
#5180000
b1000000110 #
0"
#5190000
b111100 $
b1000000111 #
1"
#5200000
b1000001000 #
0"
#5210000
b111101 $
b1000001001 #
1"
#5220000
b1000001010 #
0"
#5230000
b111110 $
b1000001011 #
1"
#5240000
b1000001100 #
0"
#5250000
b111111 $
b1000001101 #
1"
#5260000
b1000001110 #
0"
#5270000
b1000000 $
b1000001111 #
1"
#5280000
b1000010000 #
0"
#5290000
b1000001 $
b1000010001 #
1"
#5300000
b1000010010 #
0"
#5310000
b1000010 $
b1000010011 #
1"
#5320000
b1000010100 #
0"
#5330000
b1000011 $
b1000010101 #
1"
#5340000
b1000010110 #
0"
#5350000
b1000100 $
b1000010111 #
1"
#5360000
b1000011000 #
0"
#5370000
b1000101 $
b1000011001 #
1"
#5380000
b1000011010 #
0"
#5390000
b1000110 $
b1000011011 #
1"
#5400000
b1000011100 #
0"
#5410000
b1000111 $
b1000011101 #
1"
#5420000
b1000011110 #
0"
#5430000
b1001000 $
b1000011111 #
1"
#5440000
b1000100000 #
0"
#5450000
b1001001 $
b1000100001 #
1"
#5460000
b1000100010 #
0"
#5470000
b1001010 $
b1000100011 #
1"
#5480000
b1000100100 #
0"
#5490000
b1001011 $
b1000100101 #
1"
#5500000
b1000100110 #
0"
#5510000
b1001100 $
b1000100111 #
1"
#5520000
b1000101000 #
0"
#5530000
b1001101 $
b1000101001 #
1"
#5540000
b1000101010 #
0"
#5550000
b1001110 $
b1000101011 #
1"
#5560000
b1000101100 #
0"
#5570000
b1001111 $
b1000101101 #
1"
#5580000
b1000101110 #
0"
#5590000
b1010000 $
b1000101111 #
1"
#5600000
b1000110000 #
0"
#5610000
b1010001 $
b1000110001 #
1"
#5620000
b1000110010 #
0"
#5630000
b1010010 $
b1000110011 #
1"
#5640000
b1000110100 #
0"
#5650000
b1010011 $
b1000110101 #
1"
#5660000
b1000110110 #
0"
#5670000
b1010100 $
b1000110111 #
1"
#5680000
b1000111000 #
0"
#5690000
b1010101 $
b1000111001 #
1"
#5700000
b1000111010 #
0"
#5710000
b1010110 $
b1000111011 #
1"
#5720000
b1000111100 #
0"
#5730000
b1010111 $
b1000111101 #
1"
#5740000
b1000111110 #
0"
#5750000
b1011000 $
b1000111111 #
1"
#5760000
b1001000000 #
0"
#5770000
b1011001 $
b1001000001 #
1"
#5780000
b1001000010 #
0"
#5790000
b1011010 $
b1001000011 #
1"
#5800000
b1001000100 #
0"
#5810000
b1011011 $
b1001000101 #
1"
#5820000
b1001000110 #
0"
#5830000
b1011100 $
b1001000111 #
1"
#5840000
b1001001000 #
0"
#5850000
b1011101 $
b1001001001 #
1"
#5860000
b1001001010 #
0"
#5870000
b1011110 $
b1001001011 #
1"
#5880000
b1001001100 #
0"
#5890000
b1011111 $
b1001001101 #
1"
#5900000
b1001001110 #
0"
#5910000
b1100000 $
b1001001111 #
1"
#5920000
b1001010000 #
0"
#5930000
b1100001 $
b1001010001 #
1"
#5940000
b1001010010 #
0"
#5950000
b1100010 $
b1001010011 #
1"
#5960000
b1001010100 #
0"
#5970000
b1100011 $
b1001010101 #
1"
#5980000
b1001010110 #
0"
#5990000
1!
b0 $
b1001010111 #
1"
#6000000
b1001011000 #
0"
