microondas/timer/HDL/terceiro_nivel/contador_mod10.v
module contador_mod10(
    input [3:0] data,
    input loadn, clrn, clk, en,
    output reg [3:0] unidades = 4'b0000,
    output tc, zero     // tc = terminal count; indica quando o contador está no seu valor minímo
); 

    assign zero = (unidades == 4'b0000);
    assign tc = zero & en;
 
    always @(posedge clk or negedge clrn) 
        if (!clrn) begin 
            unidades <= 4'b0000;
        end
        else if (en) begin
            if (unidades == 4'b0000) begin
                unidades <= 4'b1001;
            end 
            else begin
                unidades <= unidades - 1;
            end
        end
        else if (!loadn) begin
            unidades <= data;
        end

endmodule

microondas/timer/HDL/terceiro_nivel/contador_mod6.v
module contador_mod6(
    input [3:0] data,
    input loadn, clrn, clk, en,
    output reg [3:0] dezenas = 3'b000,
    output tc, zero     // tc = terminal count; indica quando o contador está no seu valor minímo
);

    assign zero = (dezenas == 3'b000);
    assign tc = zero & en;

    
    always @(posedge clk or negedge clrn) 
        if (!clrn) begin 
            dezenas <= 3'b000;
        end
  		else if (en) begin
            if (dezenas == 3'b000) begin
                dezenas <= 3'b101;
            end 
            else begin
                dezenas <= dezenas - 1;
            end
        end
        else if (!loadn) begin
            dezenas <= data;
        end

endmodule

microondas/timer/HDL/timer.v
`include "timer\HDL\terceiro_nivel\contador_mod6.v"
`include "timer\HDL\terceiro_nivel\contador_mod10.v"

module timer(
    input [3:0] data,
    input loadn, clrn, clk, en,
    output [3:0] seg_unidades,
    output [3:0] seg_dezenas,
    output [3:0] minutos,
    output zero
);

    wire tc_unidades, tc_dezenas, tc_minutos;
    wire zero_unidades, zero_dezenas, zero_minutos;

    contador_mod10 s_unidades (
        .data(data), .loadn(loadn), .clrn(clrn), .clk(clk), .en(en), .unidades(seg_unidades),
        .tc(tc_unidades), .zero(zero_unidades)
    );
    contador_mod6 s_dezenas (
        .data(seg_unidades), .loadn(loadn), .clrn(clrn), .clk(clk), .en(tc_unidades), .dezenas(seg_dezenas),
        .tc(tc_dezenas), .zero(zero_dezenas)
    );
    contador_mod10 mins (.data(seg_dezenas), .loadn(loadn), .clrn(clrn), .clk(clk), .en(tc_dezenas), .unidades(minutos), 
    .tc(tc_minutos), .zero(zero_minutos));

    assign zero = (zero_unidades & zero_dezenas & zero_minutos) ? 1 : 0;
endmodule

microondas/timer/teste/timer/timer_tb.v
`timescale 1ns/1ps
`include "timer\HDL\timer.v"

module timer_tb;
    reg [3:0] data;
    reg loadn, clrn, clk, en;

    wire [3:0] seg_unidades;
    wire [3:0] seg_dezenas;
    wire [3:0] minutos;
    wire zero;

    integer i;

    timer dut (
        .data(data), .loadn(loadn), .clrn(clrn), .clk(clk), .en(en), 
        .seg_unidades(seg_unidades), .seg_dezenas(seg_dezenas), .minutos(minutos), .zero(zero)
    );

    initial begin
      $dumpfile("timer.vcd");
      $dumpvars(0, timer_tb);
		
      en = 0;

      /* testando a habilidade do timer de carregar digítos quando enable = 0
      e de ignorar os zeros à esquerda */
      data = 4'b0001; loadn = 0; clk = 1;
      #50;
      loadn = 1; clk = 0;
      #50;
      data = 4'b0010; loadn = 0; clk = 1;
      #50;
      loadn = 1; clk = 0;
      #50;
      data = 4'b1001; loadn = 0; clk = 1;
      #50;
      loadn = 1; clk = 0;
      #100;

      en = 1;
      // testando a contagem do timer com enable = 1
      repeat(100)
        #10 clk = ~clk;
    end
endmodule

microondas/timer/teste/timer/timer.vcd
$date
	Sun Apr 23 14:39:56 2023
$end
$version
	Icarus Verilog
$end
$timescale
	1ps
$end
$scope module timer_tb $end
$var wire 1 ! zero $end
$var wire 4 " seg_unidades [3:0] $end
$var wire 4 # seg_dezenas [3:0] $end
$var wire 4 $ minutos [3:0] $end
$var reg 1 % clk $end
$var reg 1 & clrn $end
$var reg 4 ' data [3:0] $end
$var reg 1 ( en $end
$var reg 1 ) loadn $end
$scope module dut $end
$var wire 1 % clk $end
$var wire 1 & clrn $end
$var wire 4 * data [3:0] $end
$var wire 1 ( en $end
$var wire 1 ) loadn $end
$var wire 1 + zero_unidades $end
$var wire 1 , zero_minutos $end
$var wire 1 - zero_dezenas $end
$var wire 1 ! zero $end
$var wire 1 . tc_unidades $end
$var wire 1 / tc_minutos $end
$var wire 1 0 tc_dezenas $end
$var wire 4 1 seg_unidades [3:0] $end
$var wire 4 2 seg_dezenas [3:0] $end
$var wire 4 3 minutos [3:0] $end
$scope module mins $end
$var wire 1 % clk $end
$var wire 1 & clrn $end
$var wire 1 ) loadn $end
$var wire 1 / tc $end
$var wire 1 , zero $end
$var wire 1 0 en $end
$var wire 4 4 data [3:0] $end
$var reg 4 5 unidades [3:0] $end
$upscope $end
$scope module s_dezenas $end
$var wire 1 % clk $end
$var wire 1 & clrn $end
$var wire 1 ) loadn $end
$var wire 1 0 tc $end
$var wire 1 - zero $end
$var wire 1 . en $end
$var wire 4 6 data [3:0] $end
$var reg 4 7 dezenas [3:0] $end
$upscope $end
$scope module s_unidades $end
$var wire 1 % clk $end
$var wire 1 & clrn $end
$var wire 4 8 data [3:0] $end
$var wire 1 ( en $end
$var wire 1 ) loadn $end
$var wire 1 . tc $end
$var wire 1 + zero $end
$var reg 4 9 unidades [3:0] $end
$upscope $end
$upscope $end
$upscope $end
$enddefinitions $end
#0
$dumpvars
b1 9
b1 8
b0 7
b1 6
b0 5
b0 4
b0 3
b0 2
b1 1
00
0/
0.
1-
1,
0+
b1 *
0)
0(
b1 '
x&
1%
b0 $
b0 #
b1 "
0!
$end
#50000
0%
1)
#100000
0-
b1 #
b1 2
b1 4
b1 7
b10 "
b10 1
b10 6
b10 9
1%
0)
b10 '
b10 *
b10 8
#150000
0%
1)
#200000
b1001 "
b1001 1
b1001 6
b1001 9
b10 #
b10 2
b10 4
b10 7
0,
b1 $
b1 3
b1 5
1%
0)
b1001 '
b1001 *
b1001 8
#250000
0%
1)
#350000
1(
#360000
b1000 "
b1000 1
b1000 6
b1000 9
1%
#370000
0%
#380000
b111 "
b111 1
b111 6
b111 9
1%
#390000
0%
#400000
b110 "
b110 1
b110 6
b110 9
1%
#410000
0%
#420000
b101 "
b101 1
b101 6
b101 9
1%
#430000
0%
#440000
b100 "
b100 1
b100 6
b100 9
1%
#450000
0%
#460000
b11 "
b11 1
b11 6
b11 9
1%
#470000
0%
#480000
b10 "
b10 1
b10 6
b10 9
1%
#490000
0%
#500000
b1 "
b1 1
b1 6
b1 9
1%
#510000
0%
#520000
1.
1+
b0 "
b0 1
b0 6
b0 9
1%
#530000
0%
#540000
0.
0+
b1001 "
b1001 1
b1001 6
b1001 9
b1 #
b1 2
b1 4
b1 7
1%
#550000
0%
#560000
b1000 "
b1000 1
b1000 6
b1000 9
1%
#570000
0%
#580000
b111 "
b111 1
b111 6
b111 9
1%
#590000
0%
#600000
b110 "
b110 1
b110 6
b110 9
1%
#610000
0%
#620000
b101 "
b101 1
b101 6
b101 9
1%
#630000
0%
#640000
b100 "
b100 1
b100 6
b100 9
1%
#650000
0%
#660000
b11 "
b11 1
b11 6
b11 9
1%
#670000
0%
#680000
b10 "
b10 1
b10 6
b10 9
1%
#690000
0%
#700000
b1 "
b1 1
b1 6
b1 9
1%
#710000
0%
#720000
1.
1+
b0 "
b0 1
b0 6
b0 9
1%
#730000
0%
#740000
0.
00
0+
b1001 "
b1001 1
b1001 6
b1001 9
1-
b0 #
b0 2
b0 4
b0 7
1%
#750000
0%
#760000
b1000 "
b1000 1
b1000 6
b1000 9
1%
#770000
0%
#780000
b111 "
b111 1
b111 6
b111 9
1%
#790000
0%
#800000
b110 "
b110 1
b110 6
b110 9
1%
#810000
0%
#820000
b101 "
b101 1
b101 6
b101 9
1%
#830000
0%
#840000
b100 "
b100 1
b100 6
b100 9
1%
#850000
0%
#860000
b11 "
b11 1
b11 6
b11 9
1%
#870000
0%
#880000
b10 "
b10 1
b10 6
b10 9
1%
#890000
0%
#900000
b1 "
b1 1
b1 6
b1 9
1%
#910000
0%
#920000
10
1.
1+
b0 "
b0 1
b0 6
b0 9
1%
#930000
0%
#940000
0!
0.
00
0/
0+
b1001 "
b1001 1
b1001 6
b1001 9
0-
b101 #
b101 2
b101 4
b101 7
1,
b0 $
b0 3
b0 5
1%
#950000
0%
#960000
b1000 "
b1000 1
b1000 6
b1000 9
1%
#970000
0%
#980000
b111 "
b111 1
b111 6
b111 9
1%
#990000
0%
#1000000
b110 "
b110 1
b110 6
b110 9
1%
#1010000
0%
#1020000
b101 "
b101 1
b101 6
b101 9
1%
#1030000
0%
#1040000
b100 "
b100 1
b100 6
b100 9
1%
#1050000
0%
#1060000
b11 "
b11 1
b11 6
b11 9
1%
#1070000
0%
#1080000
b10 "
b10 1
b10 6
b10 9
1%
#1090000
0%
#1100000
b1 "
b1 1
b1 6
b1 9
1%
#1110000
0%
#1120000
1.
1+
b0 "
b0 1
b0 6
b0 9
1%
#1130000
0%
#1140000
0.
0+
b1001 "
b1001 1
b1001 6
b1001 9
b100 #
b100 2
b100 4
b100 7
1%
#1150000
0%
#1160000
b1000 "
b1000 1
b1000 6
b1000 9
1%
#1170000
0%
#1180000
b111 "
b111 1
b111 6
b111 9
1%
#1190000
0%
#1200000
b110 "
b110 1
b110 6
b110 9
1%
#1210000
0%
#1220000
b101 "
b101 1
b101 6
b101 9
1%
#1230000
0%
#1240000
b100 "
b100 1
b100 6
b100 9
1%
#1250000
0%
#1260000
b11 "
b11 1
b11 6
b11 9
1%
#1270000
0%
#1280000
b10 "
b10 1
b10 6
b10 9
1%
#1290000
0%
#1300000
b1 "
b1 1
b1 6
b1 9
1%
#1310000
0%
#1320000
1.
1+
b0 "
b0 1
b0 6
b0 9
1%
#1330000
0%
#1340000
0.
0+
b1001 "
b1001 1
b1001 6
b1001 9
b11 #
b11 2
b11 4
b11 7
1%
