microondas/timer/HDL/terceiro_nivel/contador_mod10.v
module contador_mod10(
    input [3:0] data,
    input loadn, clrn, clk, en,
    output reg [3:0] unidades = 4'b0000,
    output tc, zero     // tc = terminal count; indica quando o contador está no seu valor minímo
); 

    assign zero = (unidades == 4'b0000);
    assign tc = zero & en;
 
    always @(posedge clk or negedge clrn) 
        if (!clrn) begin 
            unidades <= 4'b0000;
        end
        else if (en) begin
            if (unidades == 4'b0000) begin
                unidades <= 4'b1001;
            end 
            else begin
                unidades <= unidades - 1;
            end
        end
        else if (!loadn) begin
            unidades <= data;
        end

endmodule

microondas/timer/teste/contador_mod10/contador_mod10_tb.v
`timescale 1ns/1ps
`include "timer\HDL\terceiro_nivel\contador_mod10.v"

module contador_mod10_tb;
    reg [3:0] data;
    reg loadn, clrn, clk, en;
 
    wire tc, zero;
    wire [3:0] unidades;

    contador_mod10 dut (
        .data(data), .loadn(loadn), .clrn(clrn), .clk(clk), .en(en), 
        .unidades(unidades), .tc(tc), .zero(zero)
    );
  
  	always #100 clk = ~clk; // clk tem um período de 100ns

    initial begin
      $dumpfile("contador_mod10.vcd");
      $dumpvars(0, contador_mod10_tb);
		
      // teste 1: contagem normal, interrrompida por um clear    
      clk = 1; en = 0; loadn = 0; clrn = 1;

      data = 4'b1001; #100; en = 1; loadn = 1; #1000;
      clrn = 0;
      #1000;

      // teste 2: a contagem não deve acontecer com o enable desligado
      clrn = 1; en = 0; loadn = 0; #100;
      data = 4'b0100; #100; loadn = 1; #1000;

      // teste 3: verificando se tc e zero são ativados no momento correto
      clrn = 1; en = 0; loadn = 0; #100;
      data = 4'b1001; #100; en = 1; loadn = 1; 
      #2000;

      $finish;
    end
endmodule

microondas/timer/teste/contador_mod10/contador_mod10.vcd
$date
	Sun Apr 23 14:32:41 2023
$end
$version
	Icarus Verilog
$end
$timescale
	1ps
$end
$scope module contador_mod10_tb $end
$var wire 1 ! zero $end
$var wire 4 " unidades [3:0] $end
$var wire 1 # tc $end
$var reg 1 $ clk $end
$var reg 1 % clrn $end
$var reg 4 & data [3:0] $end
$var reg 1 ' en $end
$var reg 1 ( loadn $end
$scope module dut $end
$var wire 1 $ clk $end
$var wire 1 % clrn $end
$var wire 4 ) data [3:0] $end
$var wire 1 ' en $end
$var wire 1 ( loadn $end
$var wire 1 # tc $end
$var wire 1 ! zero $end
$var reg 4 * unidades [3:0] $end
$upscope $end
$upscope $end
$enddefinitions $end
#0
$dumpvars
b1001 *
b1001 )
0(
0'
b1001 &
1%
1$
0#
b1001 "
0!
$end
#100000
1(
1'
0$
#200000
b1000 "
b1000 *
1$
#300000
0$
#400000
b111 "
b111 *
1$
#500000
0$
#600000
b110 "
b110 *
1$
#700000
0$
#800000
b101 "
b101 *
1$
#900000
0$
#1000000
b100 "
b100 *
1$
#1100000
1#
1!
b0 "
b0 *
0$
0%
#1200000
1$
#1300000
0$
#1400000
1$
#1500000
0$
#1600000
1$
#1700000
0$
#1800000
1$
#1900000
0$
#2000000
1$
#2100000
0#
0$
0(
0'
1%
#2200000
0!
b100 "
b100 *
1$
b100 &
b100 )
#2300000
0$
1(
#2400000
1$
#2500000
0$
#2600000
1$
#2700000
0$
#2800000
1$
#2900000
0$
#3000000
1$
#3100000
0$
#3200000
1$
#3300000
0$
0(
#3400000
b1001 "
b1001 *
1$
b1001 &
b1001 )
#3500000
0$
1(
1'
#3600000
b1000 "
b1000 *
1$
#3700000
0$
#3800000
b111 "
b111 *
1$
#3900000
0$
#4000000
b110 "
b110 *
1$
#4100000
0$
#4200000
b101 "
b101 *
1$
#4300000
0$
#4400000
b100 "
b100 *
1$
#4500000
0$
#4600000
b11 "
b11 *
1$
#4700000
0$
#4800000
b10 "
b10 *
1$
#4900000
0$
#5000000
b1 "
b1 *
1$
#5100000
0$
#5200000
1#
1!
b0 "
b0 *
1$
#5300000
0$
#5400000
0#
0!
b1001 "
b1001 *
1$
