microondas/codificador_input/HDL/terceiro_nivel/debouncer.v
module debouncer(
    input clr, clk,
    output delayed_output = 0
);

    reg [2:0] contador = 3'b000;

    always @(posedge clr)
        begin
            delayed_output <= 0;
            contador = 3'b000;
        end

    always @(posedge clk)
        begin
            if (contador < 3'b111 & (!clr)) begin
                contador = contador + 1;
            end

            if (contador >= 3'b100) begin
                delayed_output <= 1;
            end
        end
endmodule

microondas/codificador_input/teste/debouncer/debouncer_tb.v
`timescale 1ns/1ps
`include "codificador_input\HDL\terceiro_nivel\debouncer.v"

module debouncer_tb;
    reg clr, clk;
 
    wire out;

    debouncer dut(
        .clr(clr), .clk(clk),
        .delayed_output(out)
    );

  	always #100 clk = ~clk;

    initial begin
        $dumpfile("debouncer.vcd");
        $dumpvars(0, debouncer_tb);
		
        clk = 1; clr = 0;
        #1500;
        clr = 0; #500;
        clr = 1; #500;
        clr = 0; #500;
        clr = 1; #500;
        clr = 1; #500;
        clr = 0; #500;
        clr = 0; #500;
        clr = 1; #500;
        $finish;
    end
endmodule

microondas/codificador_input/teste/debouncer/debouncer.vcd
$date
	Sun Apr 23 14:49:06 2023
$end
$version
	Icarus Verilog
$end
$timescale
	1ps
$end
$scope module debouncer_tb $end
$var wire 1 ! out $end
$var reg 1 " clk $end
$var reg 1 # clr $end
$scope module dut $end
$var wire 1 " clk $end
$var wire 1 # clr $end
$var reg 3 $ contador [2:0] $end
$var reg 1 ! delayed_output $end
$upscope $end
$upscope $end
$enddefinitions $end
#0
$dumpvars
b1 $
0#
1"
0!
$end
#100000
0"
#200000
b10 $
1"
#300000
0"
#400000
b11 $
1"
#500000
0"
#600000
1!
b100 $
1"
#700000
0"
#800000
b101 $
1"
#900000
0"
#1000000
b110 $
1"
#1100000
0"
#1200000
b111 $
1"
#1300000
0"
#1400000
1"
#1500000
0"
#1600000
1"
#1700000
0"
#1800000
1"
#1900000
0"
#2000000
0!
b0 $
1"
1#
#2100000
0"
#2200000
1"
#2300000
0"
#2400000
1"
#2500000
0"
0#
#2600000
b1 $
1"
#2700000
0"
#2800000
b10 $
1"
#2900000
0"
#3000000
b0 $
1"
1#
#3100000
0"
#3200000
1"
#3300000
0"
#3400000
1"
#3500000
0"
#3600000
1"
#3700000
0"
#3800000
1"
#3900000
0"
#4000000
b1 $
1"
0#
#4100000
0"
#4200000
b10 $
1"
#4300000
0"
#4400000
b11 $
1"
#4500000
0"
#4600000
1!
b100 $
1"
#4700000
0"
#4800000
b101 $
1"
#4900000
0"
#5000000
0!
b0 $
1"
1#
