microondas/codificador_input/HDL/terceiro_nivel/mux.v
module mux(
    input sel, i0, i1,
    output reg out
);

    always @(sel, i0, i1)
        begin
            case(sel)
                0: out <= i0;
                1: out <= i1;
            endcase
        end
endmodule

microondas/codificador_input/HDL/terceiro_nivel/clk_freq.v
module clk_freq(input clk_in, output reg clk_out = 0);
  reg [6:0] contador = 0;

  always @(posedge clk_in) begin
    if (contador == 99) begin
      contador <= 0; 
      clk_out <= ~clk_out; 
    end else begin
      contador <= contador + 1;
    end
  end

endmodule

microondas/codificador_input/HDL/terceiro_nivel/debouncer.v
module debouncer(
    input clr, clk,
    output delayed_output = 0
);

    reg [2:0] contador = 3'b000;

    always @(posedge clr)
        begin
            delayed_output <= 0;
            contador = 3'b000;
        end

    always @(posedge clk)
        begin
            if (contador < 3'b111 & (!clr)) begin
                contador = contador + 1;
            end

            if (contador >= 3'b100) begin
                delayed_output <= 1;
            end
        end
endmodule

microondas/codificador_input/HDL/terceiro_nivel/codificador.v
module codificador(
    input [9:0] teclado,
    input enablen,
    output reg [3:0] BCD, 
    output reg valido);

always @(teclado)
    if (!enablen) begin
        BCD = 4'b0000;
        valido = 0;
    end else begin
        case (teclado)
            10'b1000000000 : begin BCD = 4'b1001; valido = 0; end
            10'b0100000000 : begin BCD = 4'b1000; valido = 0; end
            10'b0010000000 : begin BCD = 4'b0111; valido = 0; end
            10'b0001000000 : begin BCD = 4'b0110; valido = 0; end
            10'b0000100000 : begin BCD = 4'b0101; valido = 0; end
            10'b0000010000 : begin BCD = 4'b0100; valido = 0; end
            10'b0000001000 : begin BCD = 4'b0011; valido = 0; end
            10'b0000000100 : begin BCD = 4'b0010; valido = 0; end
            10'b0000000010 : begin BCD = 4'b0001; valido = 0; end
            10'b0000000001 : begin BCD = 4'b0000; valido = 0; end
            default: begin BCD = 4'b0000; valido = 1; end
        endcase
    end
endmodule

microondas/codificador_input/HDL/codificador_input.v
`include "codificador_input\HDL\terceiro_nivel\clk_freq.v"
`include "codificador_input\HDL\terceiro_nivel\codificador.v"
`include "codificador_input\HDL\terceiro_nivel\debouncer.v"
`include "codificador_input\HDL\terceiro_nivel\mux.v"


module codificador_input(
    input [9:0] teclado,
    input clk100Hz, enablen,
    output [3:0] out_codificado,
    output loadn, pgt_1Hz
);

    wire i0, i1;


    codificador p_encoder (
        .teclado(teclado), .enablen(enablen), .BCD(out_codificado), .valido(loadn)
    );

    debouncer delay (
        .clr(loadn), .clk(clk100Hz), .delayed_output(i1)
    );

    clk_freq clk_conversao (
        .clk_in(clk100Hz), .clk_out(i0)
    );


    mux select (
        .sel(enablen), .i0(i0), .i1(i1), .out(pgt_1Hz)
    );
endmodule

microondas/codificador_input/teste/codificador_input/codificador_input_tb.v
`timescale 1ns/1ps
`include "codificador_input\HDL\codificador_input.v"

module codificador_input_tb;
    reg [9:0] teclado;
    reg clk100Hz, enablen;

    wire [3:0] out_codificado;
    wire loadn, pgt_1Hz;

    codificador_input dut(
        .teclado(teclado), .clk100Hz(clk100Hz), .enablen(enablen),
        .out_codificado(out_codificado), .loadn(loadn), .pgt_1Hz(pgt_1Hz)
    );

  	always #10 clk100Hz = ~clk100Hz; // clk tem um período de 10ns

    initial begin
        $dumpfile("codificador_input.vcd");
        $dumpvars(0, codificador_input_tb);
		
        clk100Hz = 1;  enablen = 1;

        teclado = 10'b1000000000; #200;
        teclado = 10'b0100000000; #200;
        teclado = 10'b0010000000; #200;
        teclado = 10'b0001000000; #200;
        teclado = 10'b0000100000; #200;
        teclado = 10'b0000010000; #200;
        teclado = 10'b0000001000; #200;
        teclado = 10'b0000000100; #200;
        teclado = 10'b0000000010; #200;
        teclado = 10'b0000000001; #200;
        teclado = 10'b0000000000; #200;

        $finish;
    end
endmodule

microondas/codificador_input/teste/codificador_input/codificador_input.vcd
$date
	Sun Apr 23 14:56:49 2023
$end
$version
	Icarus Verilog
$end
$timescale
	1ps
$end
$scope module codificador_input_tb $end
$var wire 1 ! pgt_1Hz $end
$var wire 4 " out_codificado [3:0] $end
$var wire 1 # loadn $end
$var reg 1 $ clk100Hz $end
$var reg 1 % enablen $end
$var reg 10 & teclado [9:0] $end
$scope module dut $end
$var wire 1 $ clk100Hz $end
$var wire 1 % enablen $end
$var wire 10 ' teclado [9:0] $end
$var wire 1 ! pgt_1Hz $end
$var wire 4 ( out_codificado [3:0] $end
$var wire 1 # loadn $end
$var wire 1 ) i1 $end
$var wire 1 * i0 $end
$scope module clk_conversao $end
$var wire 1 $ clk_in $end
$var reg 1 * clk_out $end
$var reg 7 + contador [6:0] $end
$upscope $end
$scope module delay $end
$var wire 1 $ clk $end
$var wire 1 # clr $end
$var reg 3 , contador [2:0] $end
$var reg 1 ) delayed_output $end
$upscope $end
$scope module p_encoder $end
$var wire 1 % enablen $end
$var wire 10 - teclado [9:0] $end
$var reg 4 . BCD [3:0] $end
$var reg 1 # valido $end
$upscope $end
$scope module select $end
$var wire 1 * i0 $end
$var wire 1 ) i1 $end
$var wire 1 % sel $end
$var reg 1 ! out $end
$upscope $end
$upscope $end
$upscope $end
$enddefinitions $end
#0
$dumpvars
b1001 .
b1000000000 -
b0 ,
b1 +
0*
0)
b1001 (
b1000000000 '
b1000000000 &
1%
1$
0#
b1001 "
0!
$end
#10000
0$
#20000
b10 +
b1 ,
1$
#30000
0$
#40000
b11 +
b10 ,
1$
#50000
0$
#60000
b100 +
b11 ,
1$
#70000
0$
#80000
1!
1)
b101 +
b100 ,
1$
#90000
0$
#100000
b110 +
b101 ,
1$
#110000
0$
#120000
b111 +
b110 ,
1$
#130000
0$
#140000
b1000 +
b111 ,
1$
#150000
0$
#160000
b1001 +
1$
#170000
0$
#180000
b1010 +
1$
#190000
0$
#200000
b1011 +
b1000 "
b1000 (
b1000 .
1$
b100000000 &
b100000000 '
b100000000 -
#210000
0$
#220000
b1100 +
1$
#230000
0$
#240000
b1101 +
1$
#250000
0$
#260000
b1110 +
1$
#270000
0$
#280000
b1111 +
1$
#290000
0$
#300000
b10000 +
1$
#310000
0$
#320000
b10001 +
1$
#330000
0$
#340000
b10010 +
1$
#350000
0$
#360000
b10011 +
1$
#370000
0$
#380000
b10100 +
1$
#390000
0$
#400000
b10101 +
b111 "
b111 (
b111 .
1$
b10000000 &
b10000000 '
b10000000 -
#410000
0$
#420000
b10110 +
1$
#430000
0$
#440000
b10111 +
1$
#450000
0$
#460000
b11000 +
1$
#470000
0$
#480000
b11001 +
1$
#490000
0$
#500000
b11010 +
1$
#510000
0$
#520000
b11011 +
1$
#530000
0$
#540000
b11100 +
1$
#550000
0$
#560000
b11101 +
1$
#570000
0$
#580000
b11110 +
1$
#590000
0$
#600000
b11111 +
b110 "
b110 (
b110 .
1$
b1000000 &
b1000000 '
b1000000 -
#610000
0$
#620000
b100000 +
1$
#630000
0$
#640000
b100001 +
1$
#650000
0$
#660000
b100010 +
1$
#670000
0$
#680000
b100011 +
1$
#690000
0$
#700000
b100100 +
1$
#710000
0$
#720000
b100101 +
1$
#730000
0$
#740000
b100110 +
1$
#750000
0$
#760000
b100111 +
1$
#770000
0$
#780000
b101000 +
1$
#790000
0$
#800000
b101001 +
b101 "
b101 (
b101 .
1$
b100000 &
b100000 '
b100000 -
#810000
0$
#820000
b101010 +
1$
#830000
0$
#840000
b101011 +
1$
#850000
0$
#860000
b101100 +
1$
#870000
0$
#880000
b101101 +
1$
#890000
0$
#900000
b101110 +
1$
#910000
0$
#920000
b101111 +
1$
#930000
0$
#940000
b110000 +
1$
#950000
0$
#960000
b110001 +
1$
#970000
0$
#980000
b110010 +
1$
#990000
0$
#1000000
b110011 +
b100 "
b100 (
b100 .
1$
b10000 &
b10000 '
b10000 -
#1010000
0$
#1020000
b110100 +
1$
#1030000
0$
#1040000
b110101 +
1$
#1050000
0$
#1060000
b110110 +
1$
#1070000
0$
#1080000
b110111 +
1$
#1090000
0$
#1100000
b111000 +
1$
#1110000
0$
#1120000
b111001 +
1$
#1130000
0$
#1140000
b111010 +
1$
#1150000
0$
#1160000
b111011 +
1$
#1170000
0$
#1180000
b111100 +
1$
#1190000
0$
#1200000
b111101 +
b11 "
b11 (
b11 .
1$
b1000 &
b1000 '
b1000 -
#1210000
0$
#1220000
b111110 +
1$
#1230000
0$
#1240000
b111111 +
1$
#1250000
0$
#1260000
b1000000 +
1$
#1270000
0$
#1280000
b1000001 +
1$
#1290000
0$
#1300000
b1000010 +
1$
#1310000
0$
#1320000
b1000011 +
1$
#1330000
0$
#1340000
b1000100 +
1$
#1350000
0$
#1360000
b1000101 +
1$
#1370000
0$
#1380000
b1000110 +
1$
#1390000
0$
#1400000
b1000111 +
b10 "
b10 (
b10 .
1$
b100 &
b100 '
b100 -
#1410000
0$
#1420000
b1001000 +
1$
#1430000
0$
#1440000
b1001001 +
1$
#1450000
0$
#1460000
b1001010 +
1$
#1470000
0$
#1480000
b1001011 +
1$
#1490000
0$
#1500000
b1001100 +
1$
#1510000
0$
#1520000
b1001101 +
1$
#1530000
0$
#1540000
b1001110 +
1$
#1550000
0$
#1560000
b1001111 +
1$
#1570000
0$
#1580000
b1010000 +
1$
#1590000
0$
#1600000
b1010001 +
b1 "
b1 (
b1 .
1$
b10 &
b10 '
b10 -
#1610000
0$
#1620000
b1010010 +
1$
#1630000
0$
#1640000
b1010011 +
1$
#1650000
0$
#1660000
b1010100 +
1$
#1670000
0$
#1680000
b1010101 +
1$
#1690000
0$
#1700000
b1010110 +
1$
#1710000
0$
#1720000
b1010111 +
1$
#1730000
0$
#1740000
b1011000 +
1$
#1750000
0$
#1760000
b1011001 +
1$
#1770000
0$
#1780000
b1011010 +
1$
#1790000
0$
#1800000
b1011011 +
b0 "
b0 (
b0 .
1$
b1 &
b1 '
b1 -
#1810000
0$
#1820000
b1011100 +
1$
#1830000
0$
#1840000
b1011101 +
1$
#1850000
0$
#1860000
b1011110 +
1$
#1870000
0$
#1880000
b1011111 +
1$
#1890000
0$
#1900000
b1100000 +
1$
#1910000
0$
#1920000
b1100001 +
1$
#1930000
0$
#1940000
b1100010 +
1$
#1950000
0$
#1960000
b1100011 +
1$
#1970000
0$
#1980000
1*
b0 +
1$
#1990000
0$
#2000000
0!
0)
b1 +
b0 ,
1#
1$
b0 &
b0 '
b0 -
#2010000
0$
#2020000
b10 +
1$
#2030000
0$
#2040000
b11 +
1$
#2050000
0$
#2060000
b100 +
1$
#2070000
0$
#2080000
b101 +
1$
#2090000
0$
#2100000
b110 +
1$
#2110000
0$
#2120000
b111 +
1$
#2130000
0$
#2140000
b1000 +
1$
#2150000
0$
#2160000
b1001 +
1$
#2170000
0$
#2180000
b1010 +
1$
#2190000
0$
#2200000
b1011 +
1$
