microondas/codificador_input/HDL/terceiro_nivel/codificador.v
module codificador(
    input [9:0] teclado,
    input enablen,
    output reg [3:0] BCD, 
    output reg valido);

always @(teclado)
    if (!enablen) begin
        BCD = 4'b0000;
        valido = 0;
    end else begin
        case (teclado)
            10'b1000000000 : begin BCD = 4'b1001; valido = 0; end
            10'b0100000000 : begin BCD = 4'b1000; valido = 0; end
            10'b0010000000 : begin BCD = 4'b0111; valido = 0; end
            10'b0001000000 : begin BCD = 4'b0110; valido = 0; end
            10'b0000100000 : begin BCD = 4'b0101; valido = 0; end
            10'b0000010000 : begin BCD = 4'b0100; valido = 0; end
            10'b0000001000 : begin BCD = 4'b0011; valido = 0; end
            10'b0000000100 : begin BCD = 4'b0010; valido = 0; end
            10'b0000000010 : begin BCD = 4'b0001; valido = 0; end
            10'b0000000001 : begin BCD = 4'b0000; valido = 0; end
            default: begin BCD = 4'b0000; valido = 1; end
        endcase
    end
endmodule

microondas/codificador_input/teste/codificador/codificador_tb.v
`timescale 1ns/1ps
`include "codificador_input\HDL\terceiro_nivel\codificador.v"

module codificador_tb;
    reg [9:0] teclado;
    reg enablen;
 
    wire [3:0] BCD;
    wire valido;

    codificador dut (
        .teclado(teclado), .enablen(enablen),
        .BCD(BCD), .valido(valido)
    );

    initial begin
        $dumpfile("codificador.vcd");
        $dumpvars(0, codificador_tb);

        enablen = 1;

        teclado = 10'b1000000000; #100;
        teclado = 10'b0100000000; #100;
        teclado = 10'b0010000000; #100;
        teclado = 10'b0001000000; #100;
        teclado = 10'b0000100000; #100;
        teclado = 10'b0000010000; #100;
        teclado = 10'b0000001000; #100;
        teclado = 10'b0000000100; #100;
        teclado = 10'b0000000010; #100;
        teclado = 10'b0000000001; #100;

    end
endmodule

microondas/codificador_input/teste/codificador/codificador.vcd
$date
	Sun Apr 23 14:47:12 2023
$end
$version
	Icarus Verilog
$end
$timescale
	1ps
$end
$scope module codificador_tb $end
$var wire 1 ! valido $end
$var wire 4 " BCD [3:0] $end
$var reg 1 # enablen $end
$var reg 10 $ teclado [9:0] $end
$scope module dut $end
$var wire 1 # enablen $end
$var wire 10 % teclado [9:0] $end
$var reg 4 & BCD [3:0] $end
$var reg 1 ! valido $end
$upscope $end
$upscope $end
$enddefinitions $end
#0
$dumpvars
b1001 &
b1000000000 %
b1000000000 $
1#
b1001 "
0!
$end
#100000
b1000 "
b1000 &
b100000000 $
b100000000 %
#200000
b111 "
b111 &
b10000000 $
b10000000 %
#300000
b110 "
b110 &
b1000000 $
b1000000 %
#400000
b101 "
b101 &
b100000 $
b100000 %
#500000
b100 "
b100 &
b10000 $
b10000 %
#600000
b11 "
b11 &
b1000 $
b1000 %
#700000
b10 "
b10 &
b100 $
b100 %
#800000
b1 "
b1 &
b10 $
b10 %
#900000
b0 "
b0 &
b1 $
b1 %
